{
	"homePage": {
		"header_text": "<b>HELIOS HOSPITAL MANAGEMENT SYSTEM",
		"logo": "/bahmni_config/openmrs/apps/home/helios.png",
		"title_text": " "
	},
	"loginPage": {
		"logo": "/bahmni_config/openmrs/apps/home/helios.png",
		"showHeaderText": true,
		"showTitleText": false
	},
	"helpLink": {
		"url": "https://1or8.com.np"
	},
	"landingPage": [
		{
			"enabled": true,
			"name": "clinicalService",
			"title": "Clinical Service",
			"logo": "/bahmni_config/openmrs/apps/home/app.png",
			"link": "/bahmni/home"
		},
		{
			"enabled": true,
			"name": "openelis",
			"title": "Laboratory",
			"logo": "/bahmni_config/openmrs/apps/home/lab.png",
			"link": "/openelis"
		},
		{
			"enabled": true,
			"name": "odoo",
			"title": "Inventory & Bills",
			"logo": "/bahmni_config/openmrs/apps/home/bills.png",
			"linkPrefix": "erp"
		},
		{
			"enabled": false,
			"name": "crater",
			"title": "Payment & Bills",
			"logo": "/bahmni_config/openmrs/apps/home/bills.png",
			"linkPrefix": "payments"
		},
		{
			"enabled": false,
			"name": "connect",
			"title": "Connect",
			"logo": "/bahmni_config/openmrs/apps/home/connect.png",
			"link": "/bahmni-connect"
		},
		{
			"enabled": true,
			"name": "dcm",
			"title": "Radiology",
			"logo": "/bahmni_config/openmrs/apps/home/pacs.png",
			"link": "/dcm4chee-web3"
		},
		{
			"enabled": true,
			"name": "metabase",
			"title": "Analytics",
			"logo": "/bahmni_config/openmrs/apps/home/analytics.png",
			"link": "/metabase"
		}
	]
}
